chemgraph/__init__.py
chemgraph/plot_module.py
chemgraph-0.0.14.dist-info/LICENSE
chemgraph-0.0.14.dist-info/METADATA
chemgraph-0.0.14.dist-info/WHEEL
chemgraph-0.0.14.dist-info/top_level.txt
chemgraph-0.0.14.dist-info/RECORD
